mirmeter/__init__.py
mirmeter/__main__.py
mirmeter/client.py
mirmeter-0.1.1.dist-info/METADATA
mirmeter-0.1.1.dist-info/WHEEL
mirmeter-0.1.1.dist-info/licenses/LICENSE
mirmeter-0.1.1.dist-info/RECORD
