Metadata-Version: 2.4
Name: mirmeter
Version: 0.1.1
Summary: MIR meter customer display
Project-URL: Homepage, https://github.com/Hal9k0/mirmeter
Project-URL: Issues, https://github.com/Hal9k0/mirmeter/issues
Author-email: Hal9k <mir@hal9k.ru>
License-Expression: MIT
License-File: LICENSE
Classifier: License :: Free For Home Use
Classifier: License :: Free for non-commercial use
Classifier: License :: OSI Approved :: MIT License
Classifier: Natural Language :: Russian
Classifier: Operating System :: OS Independent
Classifier: Programming Language :: Python :: 3
Requires-Python: >=3.8
